[
  {
    "id": "67604187-57c3-4be6-987c-ea4bef388ad3",
    "firstName": "Abdur-Rahmaan",
    "lastName": "Janhangeer",
    "fullName": "Abdur-Rahmaan Janhangeer",
    "bio": "A random programmer who dipped, landed deep in Python waters and got featured along the way as PyDev of The Week.",
    "tagLine": "Python Developer",
    "profilePicture": "https://sessionize.com/image/f1ef-400o400o2-87-57c3-4be6-987c-ea4bef388ad3.615285f7-19eb-452c-b5c1-b68b53f082c7.jpeg",
    "sessions": [
      {
        "id": 302837,
        "name": "Fast Flask Dev With Big Codebases"
      },
      {
        "id": 302838,
        "name": "Python Bytecode or how Python operates"
      },
      {
        "id": 302840,
        "name": "How To OpenSource"
      }
    ],
    "isTopSpeaker": false,
    "links": [
      {
        "title": "Twitter",
        "url": "https://twitter.com/osdotsystem",
        "linkType": "Twitter"
      },
      {
        "title": "LinkedIn",
        "url": "https://www.linkedin.com/in/appinv/",
        "linkType": "LinkedIn"
      },
      {
        "title": "Blog",
        "url": "https://www.pythonkitchen.com",
        "linkType": "Blog"
      }
    ],
    "questionAnswers": [],
    "categories": []
  },
  {
    "id": "dde46c59-2d2b-4840-b7a1-131c373e556d",
    "firstName": "Aditya",
    "lastName": "Bholah",
    "fullName": "Aditya Bholah",
    "bio": "Data Science, AI and Python enthusiast with an educational background in law and computer science. Contributor in PSF and currently active in local community (ISOC, LUGM).",
    "tagLine": "Data Analyst @ RAPP IO",
    "profilePicture": "https://sessionize.com/image/6e72-400o400o2-59-2d2b-4840-b7a1-131c373e556d.f0c4ff2b-f1df-4075-9bcd-dda76676b32d.jpg",
    "sessions": [
      {
        "id": 290931,
        "name": "Hadoop For Noobs"
      }
    ],
    "isTopSpeaker": false,
    "links": [
      {
        "title": "Twitter",
        "url": "https://twitter.com/aditya_bholah",
        "linkType": "Twitter"
      },
      {
        "title": "Blog",
        "url": "https://thecuriouschap.com",
        "linkType": "Blog"
      }
    ],
    "questionAnswers": [],
    "categories": []
  },
  {
    "id": "8c630b80-917e-4ce6-901f-ac626f1223b2",
    "firstName": "Alan",
    "lastName": "Jean",
    "fullName": "Alan Jean",
    "bio": "Full-Time Digitaloholic\r\nAmbassador of Buzz around Containers                                          Master Orchestrator of LED Blinking",
    "tagLine": "Technical Architect - Stratalis Ltd.",
    "profilePicture": "https://sessionize.com/image/95ed-400o400o2-Uh9QNSUAEVCWhe7xFwFs5d.jpeg",
    "sessions": [
      {
        "id": 302839,
        "name": "Building Production-Ready Swarm Clusters on Docker-CE"
      }
    ],
    "isTopSpeaker": false,
    "links": [
      {
        "title": "LinkedIn",
        "url": "https://www.linkedin.com/in/alan-jean/",
        "linkType": "LinkedIn"
      }
    ],
    "questionAnswers": [],
    "categories": []
  },
  {
    "id": "dd1aaf3b-c86a-4758-aa38-aaad2d7dd9e8",
    "firstName": "Alexandre",
    "lastName": "Bazile",
    "fullName": "Alexandre Bazile",
    "bio": "Alexandre Bazile is an hyperactive technology enthusiast who always like to feed his technology adventure thrills. From mobile apps to desktop apps to cloud scale apps, he never misses an opportunity to breathe into a new technology. Good Design patterns and app architecture are his hot topics, but when he is not talking about coding, he's wondering what would be the next great SaaS solution. ",
    "tagLine": "Technology Enthusiast and Independent Consultant",
    "profilePicture": "https://sessionize.com/image/c116-400o400o2-Nz21WzTdAYTQowCUD6uJaM.png",
    "sessions": [
      {
        "id": 302435,
        "name": "The Full Stack Journey, A Rich and Fulfilling, But Challenging Path!"
      }
    ],
    "isTopSpeaker": false,
    "links": [
      {
        "title": "Twitter",
        "url": "https://twitter.com/alexbazile",
        "linkType": "Twitter"
      },
      {
        "title": "LinkedIn",
        "url": "https://www.linkedin.com/in/alexandrebazile",
        "linkType": "LinkedIn"
      },
      {
        "title": "Blog",
        "url": "https://alexandrebazile.com",
        "linkType": "Blog"
      }
    ],
    "questionAnswers": [],
    "categories": []
  },
  {
    "id": "7a773a9d-a41a-43be-bd78-29f5786f379e",
    "firstName": "Aroun",
    "lastName": "Poligadu",
    "fullName": "Aroun Poligadu",
    "bio": "Aroun is passionate about technology and project management. He is the Chief Information Officer of iQera Indian Ocean, Founder and President of the Project Management Institute Chapter Of Mauritius. In his 18+ years in the IT industry, he has worked with customers and teams across the globe. As a senior leader, he served various roles in organisational growth strategy and led key IT programmes. He regularly speaks in conferences and events. Aroun holds a Masters Degree in software project management, is PMP certified, Agile Hybrid Pro credential holder, Organisation Transformation certification holder, IT Governance Manager certified.",
    "tagLine": "CIO @Iqera, President Project Management Institute Mauritius",
    "profilePicture": "https://sessionize.com/image/77ac-400o400o2-RUARNYcFk1b6Jw91xmvPM8.jpg",
    "sessions": [
      {
        "id": 305184,
        "name": "Digital transformation: Bridging the Gap between strategy and execution"
      }
    ],
    "isTopSpeaker": false,
    "links": [],
    "questionAnswers": [],
    "categories": []
  },
  {
    "id": "a1afe56d-adc2-40fa-a6f2-7c66ae84a525",
    "firstName": "Arvind",
    "lastName": "Ballgobin",
    "fullName": "Arvind Ballgobin",
    "bio": "Lives within the Angular Eco-system. Always curious about how it works.\r\n#TeamPlayer #Angular #AvidLearner #PHPdeveloper #Blogger\r\n",
    "tagLine": "Lead Frontend Engineer",
    "profilePicture": "https://sessionize.com/image/8bb0-400o400o2-6d-adc2-40fa-a6f2-7c66ae84a525.58c9a0b6-3a0d-4630-a06b-af35f331cd18.jpg",
    "sessions": [
      {
        "id": 373555,
        "name": "Angular Compiler in depth"
      }
    ],
    "isTopSpeaker": false,
    "links": [
      {
        "title": "LinkedIn",
        "url": "https://www.linkedin.com/in/rajendra-ballgobin-17027777/",
        "linkType": "LinkedIn"
      }
    ],
    "questionAnswers": [],
    "categories": []
  },
  {
    "id": "64bd9e33-e619-490b-aae1-b5c328d456f2",
    "firstName": "Arwin Neil",
    "lastName": "Baichoo",
    "fullName": "Arwin Neil Baichoo",
    "bio": "Tech enthusiast, geek, and software engineer.",
    "tagLine": "Software Engineer at Event Store",
    "profilePicture": "https://sessionize.com/image/36d9-400o400o2-33-e619-490b-aae1-b5c328d456f2.6a97f07d-a6bc-47e9-b7be-300b044ce378.jpg",
    "sessions": [
      {
        "id": 302548,
        "name": "A journey into open source"
      }
    ],
    "isTopSpeaker": false,
    "links": [
      {
        "title": "Twitter",
        "url": "https://twitter.com/arwinneil",
        "linkType": "Twitter"
      },
      {
        "title": "LinkedIn",
        "url": "https://linkedin.com/in/arwinneil/",
        "linkType": "LinkedIn"
      },
      {
        "title": "Blog",
        "url": "https://arwinneil.xyz",
        "linkType": "Blog"
      }
    ],
    "questionAnswers": [],
    "categories": []
  },
  {
    "id": "9d1aa6d1-b9bb-452d-b725-051703e6cd48",
    "firstName": "Ashvin",
    "lastName": "Ramanjooloo",
    "fullName": "Ashvin Ramanjooloo",
    "bio": "Ashvin is passionate about technology and software development. During his career, Ashvin has had experience in defining architectural vision and roadmap, modeling  APIs and domains and at the same time pitching technical choices to middle and upper management. He also has built and led software development teams in various sectors such as financial debt recovery, insurance, telecommunication, aviation, global logistics, network inventory\r\n \r\nAshvin also has keen interest in Domain Driven Design, devops practices and team topologies that improve software delivery performance.",
    "tagLine": "Head of Software Engineering",
    "profilePicture": "https://sessionize.com/image/2f28-400o400o2-Pgi6o9LwwD4a4U4gBYU9eJ.jpg",
    "sessions": [
      {
        "id": 302404,
        "name": "Low-code et architecture micro service"
      }
    ],
    "isTopSpeaker": false,
    "links": [
      {
        "title": "Twitter",
        "url": "https://twitter.com/ashramanjooloo",
        "linkType": "Twitter"
      },
      {
        "title": "LinkedIn",
        "url": "https://www.linkedin.com/in/ashvin-ramanjooloo/",
        "linkType": "LinkedIn"
      }
    ],
    "questionAnswers": [],
    "categories": []
  },
  {
    "id": "98590667-81a3-47e6-9c58-42a2045a293c",
    "firstName": "Avinash",
    "lastName": "Meetoo",
    "fullName": "Avinash Meetoo",
    "bio": "Computer Scientist, TEDx speaker and Head of Experimentation Accelerator Labs at United Nations Development Programme (UNDP) Mauritius & Seychelles.",
    "tagLine": "A geek from Mauritius",
    "profilePicture": "https://sessionize.com/image/a1cf-400o400o2-67-81a3-47e6-9c58-42a2045a293c.ccd84ec7-ca38-4804-b29a-ede85ecb4ac7.jpg",
    "sessions": [
      {
        "id": 302642,
        "name": "A Brief History of Programming"
      }
    ],
    "isTopSpeaker": false,
    "links": [
      {
        "title": "Twitter",
        "url": "https://twitter.com/AvinashMeetoo",
        "linkType": "Twitter"
      },
      {
        "title": "LinkedIn",
        "url": "https://www.linkedin.com/in/avinashmeetoo",
        "linkType": "LinkedIn"
      },
      {
        "title": "Blog",
        "url": "https://www.avinashmeetoo.com/",
        "linkType": "Blog"
      }
    ],
    "questionAnswers": [],
    "categories": []
  },
  {
    "id": "dd3a76fa-fceb-4f62-81a1-b8c4f087d7d2",
    "firstName": "Avish",
    "lastName": "Cheetaram",
    "fullName": "Avish Cheetaram",
    "bio": "Avish Cheetaram is a Mauritian software engineer, with strong interests in distributed systems, system design, data structures and algorithms.\r\n",
    "tagLine": "Full Stack Software Engineer at La Sentinelle. ",
    "profilePicture": "https://sessionize.com/image/0b06-400o400o2-W6UficAX9p3U66yR9RqjuX.jpg",
    "sessions": [
      {
        "id": 372612,
        "name": "Microservices Architecture"
      }
    ],
    "isTopSpeaker": false,
    "links": [
      {
        "title": "Twitter",
        "url": "https://twitter.com/Avishcybergeek",
        "linkType": "Twitter"
      },
      {
        "title": "LinkedIn",
        "url": "https://www.linkedin.com/in/avishcheetaram/",
        "linkType": "LinkedIn"
      },
      {
        "title": "Blog",
        "url": "http://www.avishcheetaram.com/",
        "linkType": "Blog"
      }
    ],
    "questionAnswers": [],
    "categories": []
  },
  {
    "id": "1fd572bd-a45d-497a-99ea-f2cec9d9b9ab",
    "firstName": "Chervine",
    "lastName": "Bhiwoo",
    "fullName": "Chervine Bhiwoo",
    "bio": "Chervine is the Engineering lead of MCB Group. He drives the strategy and implementation of MCB’s web and mobile solutions across 3 countries for several lines of business. He enjoys building motivated engineering teams with a technical style of leadership and helps the teams to continuously improve on their engineering and DevOps practices to achieve higher scale and provide a better service to MCB’s customers. Chervine also enjoys sharing his passion with other people, thus actively contributing to the technical communities, meetups, and technical conferences.",
    "tagLine": "Engineering Lead, MCB Group",
    "profilePicture": "https://sessionize.com/image/8144-400o400o2-bd-a45d-497a-99ea-f2cec9d9b9ab.48b21ff6-09cd-4a52-99e0-0364b7b28a1a.jpeg",
    "sessions": [
      {
        "id": 372534,
        "name": "Build and ship faster"
      }
    ],
    "isTopSpeaker": false,
    "links": [
      {
        "title": "Twitter",
        "url": "https://twitter.com/chervinebhiwoo",
        "linkType": "Twitter"
      },
      {
        "title": "LinkedIn",
        "url": "https://www.linkedin.com/in/chervinebhiwoo/",
        "linkType": "LinkedIn"
      },
      {
        "title": "Blog",
        "url": "https://chervine.net",
        "linkType": "Blog"
      }
    ],
    "questionAnswers": [],
    "categories": []
  },
  {
    "id": "a189d971-edd8-46d2-a69a-d561a20c681e",
    "firstName": "Chittesh",
    "lastName": "Sham ",
    "fullName": "Chittesh Sham",
    "bio": "Winner of MIT Global Startup Labs (GSL) and runner up in krakathon 2018. Experienced in setting up linux-based infrastructure services, maintaining and scaling. ",
    "tagLine": "Linux Systems Engineer",
    "profilePicture": "https://sessionize.com/image/5835-400o400o2-71-edd8-46d2-a69a-d561a20c681e.2a9afa6d-9c60-4519-9c1c-2d7a927ed274.jpg",
    "sessions": [
      {
        "id": 293629,
        "name": "Understanding the underlying stack of Linux containers - in just 5 mins"
      }
    ],
    "isTopSpeaker": false,
    "links": [],
    "questionAnswers": [],
    "categories": []
  },
  {
    "id": "84bd74f7-5904-4570-acfc-bf4250d85585",
    "firstName": "Christel ",
    "lastName": "Lim",
    "fullName": "Christel Lim",
    "bio": "An enthusiastic and passionate HR professional with nearly 15 years’ experience in Human Resources, having joined SWAN in 2008. Appointed Manager – Human Capital in 2019 and provides advice and services to all entities of SWAN, with areas of expertise including HR project implementation, process improvement, compensation and learning and development. Deeply believes in hard work, honesty, continuous improvement and values genuine people connections.",
    "tagLine": "Whatever you do, do it well and always remain true to yourself.",
    "profilePicture": "https://sessionize.com/image/ee8e-400o400o2-hRDmwXkrxDcQ4uhcLqJqF1.jpg",
    "sessions": [
      {
        "id": 380243,
        "name": "Enhancing the quality of working life "
      }
    ],
    "isTopSpeaker": false,
    "links": [],
    "questionAnswers": [],
    "categories": []
  },
  {
    "id": "918eb83c-a6bf-4827-ab96-61da6907fe1e",
    "firstName": "Didier",
    "lastName": "Bephage",
    "fullName": "Didier Bephage",
    "bio": "Technology Director at SD Worx Mauritius, a leading European provider of HR and Payroll Services that develops its own SAAS platforms, and services global customers with best of breed software applications, using a heavy contingent of IT Software Engineers based in Ebene.",
    "tagLine": "Blockchain enthusiast",
    "profilePicture": "https://sessionize.com/image/e4d2-400o400o2-44HU9Cj6nGtqQ1WBRKxyJg.jpg",
    "sessions": [
      {
        "id": 302445,
        "name": "Become a Blockchain Developer"
      }
    ],
    "isTopSpeaker": false,
    "links": [
      {
        "title": "Twitter",
        "url": "https://twitter.com/Defi_Didier",
        "linkType": "Twitter"
      },
      {
        "title": "LinkedIn",
        "url": "https://www.linkedin.com/in/didierbephage/",
        "linkType": "LinkedIn"
      },
      {
        "title": "Facebook",
        "url": "https://www.facebook.com/didier.bephage/",
        "linkType": "Facebook"
      },
      {
        "title": "Company Website",
        "url": "https://www.sdworx.com",
        "linkType": "Company_Website"
      }
    ],
    "questionAnswers": [],
    "categories": []
  },
  {
    "id": "4139ab2e-d5ee-484d-8e3f-7b8df6bf1ef4",
    "firstName": "Dina",
    "lastName": "RAKOTONIRINA",
    "fullName": "Dina RAKOTONIRINA",
    "bio": "Développeur passionné, aimant les challenges. Le goût du défi lui a permis de participer au développement de projets d'envergure. Actuellement, ses principales technologies sont orientées sur Javascript et PHP, notamment sur les frameworks Angular et Symfony. ",
    "tagLine": "Angular/Symfony Developer - KLANIK",
    "profilePicture": "https://sessionize.com/image/1837-400o400o2-EnKnvWFRHf6iPApSVxhPDB.jpg",
    "sessions": [
      {
        "id": 302750,
        "name": "La gestion d'état réactive sur Angular avec NgRx"
      }
    ],
    "isTopSpeaker": false,
    "links": [
      {
        "title": "LinkedIn",
        "url": "https://www.linkedin.com/in/rdinakely/",
        "linkType": "LinkedIn"
      }
    ],
    "questionAnswers": [],
    "categories": []
  },
  {
    "id": "61d89e71-a2c1-47fe-920c-7c769b35e358",
    "firstName": "Dylan",
    "lastName": "Harbour",
    "fullName": "Dylan Harbour",
    "bio": "I lead the tech driving over a dozen marketplace platforms spread across Africa, South East Asia and Eastern Europe. \r\n\r\nWe specialise in building technology that connect buyers to sellers, and backend micro-services that empower businesses to succeed in the Jobs, Property and General Classifieds segments.\r\n\r\nThrough the platforms we support, we’ve served over 6 million listings and billions of requests. We're deep into the AWS & Laravel ecosystems and any other tech that gets the job done! ",
    "tagLine": "Director of Technology, Ringier SA",
    "profilePicture": "https://sessionize.com/image/8a29-400o400o2-SkGCTcXtmc5Ejd8sGAmung.jpg",
    "sessions": [
      {
        "id": 383770,
        "name": "How to serve billions of images, without billions of dollars."
      },
      {
        "id": 383772,
        "name": "5 Things I wish I knew about Core Web Vitals"
      }
    ],
    "isTopSpeaker": false,
    "links": [
      {
        "title": "LinkedIn",
        "url": "https://www.linkedin.com/in/%F0%9F%92%BB-dylan-harbour-96b48116a/",
        "linkType": "LinkedIn"
      }
    ],
    "questionAnswers": [],
    "categories": []
  },
  {
    "id": "ba3958ec-7d08-4845-bcb5-2e1774318932",
    "firstName": "Girish",
    "lastName": "Mahabir",
    "fullName": "Girish Mahabir",
    "bio": "Girish Mahabir is a System and Security Engineer at OceanDBA. He is specializing in Linux systems and Security, always learning and tackling challenges to contribute to making the company advances. He also contributes some of his work, personal or professional on GitLab or GitHub, basically anything that can help the community and technology advance. Girish also occupied quite some positions in the past, which helped him learn a lot of technologies and understand different architectures. Some of those technologies are Linux, Bash, Python, Elasticsearch, Logstash, Kibana, Beats, Docker, Ansible, Wazuh, LDAP and much more. \r\n\r\nWhile being an IT professional, He's also a student at the Middlesex University Mauritius studying Computer Science Systems Engineering. While in university, he helps in the IT Clubs and represents the University in Inter-University Competitions as well as organizing workshops that aim in bridging the gap that is present between the university and the Industry.\r\n",
    "tagLine": "System & Security Engineer at OceanDBA",
    "profilePicture": "https://sessionize.com/image/5a96-400o400o2-EqcsVxoSvz48U6mBwwg2bb.jpg",
    "sessions": [
      {
        "id": 301293,
        "name": "Infrastructure logging with the Elastic Stack"
      }
    ],
    "isTopSpeaker": false,
    "links": [
      {
        "title": "Twitter",
        "url": "https://twitter.com/girishmahabir",
        "linkType": "Twitter"
      },
      {
        "title": "LinkedIn",
        "url": "https://www.linkedin.com/in/girish-mahabir",
        "linkType": "LinkedIn"
      },
      {
        "title": "Facebook",
        "url": "https://www.facebook.com/girish.mahabir/",
        "linkType": "Facebook"
      },
      {
        "title": "Instagram",
        "url": "https://www.instagram.com/girish_mahabir/",
        "linkType": "Instagram"
      },
      {
        "title": "Company Website",
        "url": "https://oceandba.com/",
        "linkType": "Company_Website"
      }
    ],
    "questionAnswers": [],
    "categories": []
  },
  {
    "id": "7903c14e-9312-4e5f-8808-454c78a5ac71",
    "firstName": "Heman",
    "lastName": "Mohabeer",
    "fullName": "Heman Mohabeer",
    "bio": "Holder of a Ph.D. in Artificial Intelligence and Machine Learning, Dr. Heman Mohabeer enjoys developing AI/ML frameworks. His\r\nbackground in Artificial Intelligence, Data Analytics, and Digital transformation inform his mindful but competitive approach. Dr. Heman is\r\nfueled by his passion for understanding the nuances of Data and its ability to tell stories. He also has several publications and has travelled\r\nto several African countries to deliver lectures on AI.",
    "tagLine": "The passionate thinker",
    "profilePicture": "https://sessionize.com/image/6e2a-400o400o2-H28DWnbjiP2TJcS6HEbYQ.jpg",
    "sessions": [
      {
        "id": 306269,
        "name": "Putting AI into action in Manufacturing"
      }
    ],
    "isTopSpeaker": false,
    "links": [
      {
        "title": "LinkedIn",
        "url": "https://mu.linkedin.com/in/hemanmohabeer/",
        "linkType": "LinkedIn"
      }
    ],
    "questionAnswers": [],
    "categories": []
  },
  {
    "id": "ef7633d0-46b2-4045-bbc3-3dc1fcd55596",
    "firstName": "Ish",
    "lastName": "Sookun",
    "fullName": "Ish Sookun",
    "bio": "I am a Systems Architect at La Sentinelle Ltd. I contribute to the openSUSE Project in my free time and I maintain Linux mirrors in Mauritius. I also follow policy discussions within the AFRINIC community.",
    "tagLine": "La Sentinelle Ltd / openSUSE member",
    "profilePicture": "https://sessionize.com/image/8b70-400o400o2-d0-46b2-4045-bbc3-3dc1fcd55596.1cc03b8c-e2ed-4d40-a5dc-1d18df5236a3.png",
    "sessions": [
      {
        "id": 293919,
        "name": "Securing and managing your own mail server"
      },
      {
        "id": 293989,
        "name": "Authenticating open source cloud applications with LDAP"
      },
      {
        "id": 293915,
        "name": "Ghost theme development"
      }
    ],
    "isTopSpeaker": false,
    "links": [
      {
        "title": "Twitter",
        "url": "https://twitter.com/IshSookun",
        "linkType": "Twitter"
      },
      {
        "title": "LinkedIn",
        "url": "https://www.linkedin.com/in/ishsookun/",
        "linkType": "LinkedIn"
      },
      {
        "title": "Blog",
        "url": "https://sysadmin-journal.com",
        "linkType": "Blog"
      }
    ],
    "questionAnswers": [],
    "categories": []
  },
  {
    "id": "49af17a2-5b86-4b9b-aadc-07b99b08cc5d",
    "firstName": "Jeshta",
    "lastName": "Bhoyedhur",
    "fullName": "Jeshta Bhoyedhur",
    "bio": "Senior Software Engineer at  Publicis Prodigious Brand Logistics. I work both with Php frameworks and Golang.\r\n\r\nKeen to learn new techs.\r\n",
    "tagLine": "Senior Software Engineer, Publicis Prodigious Brand Logistics",
    "profilePicture": "https://sessionize.com/image/aa33-400o400o2-Seb6bm87x4PmoLf2GHPsSv.jpg",
    "sessions": [
      {
        "id": 300927,
        "name": "Introduction to RFC 7807 in Golang. A Better REST HTTP API Error Responses."
      }
    ],
    "isTopSpeaker": false,
    "links": [
      {
        "title": "Twitter",
        "url": "https://twitter.com/jjeshta",
        "linkType": "Twitter"
      },
      {
        "title": "LinkedIn",
        "url": "https://www.linkedin.com/in/jeshta-bhoyedhur/",
        "linkType": "LinkedIn"
      }
    ],
    "questionAnswers": [],
    "categories": []
  },
  {
    "id": "4c563acb-7ae8-4b4d-9ddf-11c19a02b813",
    "firstName": "Jochen",
    "lastName": "Kirstätter",
    "fullName": "Jochen Kirstätter",
    "bio": "Although living on a tropical island, Jochen Kirstätter is a business owner and entrepreneur in different industry sectors. Mainly operating in the development of tailor-made software solutions since more than 20 years, he is also venturing into the world of cloud computing. You can either meet him at the weekly Code & Coffee meetups of the Mauritius Software Craftsmanship Community or reach him on Twitter: @JKirstaetter.\r\n\r\nJochen is a Google Developer Expert (GDE) for Google Cloud and used to be Microsoft MVP for Developer Technologies for several years. He founded the now largest IT community in Mauritius, and organises the annual Developers Conference. Following his interest in cross-platform technologies he is also an organiser of the Google Developer Group (GDG) Mauritius.",
    "tagLine": "The only frontiers are in your mind | GDE Cloud | Microsoft MVP",
    "profilePicture": "https://sessionize.com/image/7bc3-400o400o2-H4sW5JFJFodMXwZ5jXbes6.jpg",
    "sessions": [
      {
        "id": 392806,
        "name": "Running SQL Server on GCP"
      },
      {
        "id": 392805,
        "name": "Develop .NET apps for GCP"
      }
    ],
    "isTopSpeaker": false,
    "links": [
      {
        "title": "Twitter",
        "url": "https://twitter.com/jkirstaetter",
        "linkType": "Twitter"
      },
      {
        "title": "LinkedIn",
        "url": "https://www.linkedin.com/in/jochenkirstaetter/",
        "linkType": "LinkedIn"
      },
      {
        "title": "Blog",
        "url": "https://jochen.kirstaetter.name/",
        "linkType": "Blog"
      },
      {
        "title": "Company Website",
        "url": "https://jochen.kirstaetter.name/",
        "linkType": "Company_Website"
      }
    ],
    "questionAnswers": [],
    "categories": []
  },
  {
    "id": "595f2086-76e4-44e5-afc4-ff43e505a107",
    "firstName": "Jordan",
    "lastName": "Bienvenue",
    "fullName": "Jordan Bienvenue",
    "bio": "Escaping Concrete jungle through my skilled.",
    "tagLine": "Frontend Developer - Drone Pilot - Beekeeper",
    "profilePicture": "https://sessionize.com/image/09ff-400o400o2-M2zFmfsCB38k18aaQQofJQ.jpg",
    "sessions": [
      {
        "id": 302835,
        "name": "\"Imaginative Art\" for a living"
      }
    ],
    "isTopSpeaker": false,
    "links": [
      {
        "title": "Twitter",
        "url": "https://twitter.com/JordanBienvenue",
        "linkType": "Twitter"
      },
      {
        "title": "LinkedIn",
        "url": "https://www.linkedin.com/in/jordanbienvenue/",
        "linkType": "LinkedIn"
      },
      {
        "title": "Blog",
        "url": "https://jordanbienvenue.com/",
        "linkType": "Blog"
      }
    ],
    "questionAnswers": [],
    "categories": []
  },
  {
    "id": "462e6b97-01f9-44b1-864c-9d85bedf911b",
    "firstName": "Julien",
    "lastName": "Salvi",
    "fullName": "Julien Salvi",
    "bio": "Into the Android world for 10 years, I experienced California the startup way of life before coming back to France. I am currently a Lead Android Engineer at Aircall where we are building the best phone system for modern businesses. Alongside Android, I have a great interest in backend development with Kotlin and AR/VR technology. In 2021, I became an Android GDE to continue my journey to always share and learn with the Android community.\r\nOn my spare time, I am a world traveler and a beer lover always looking for the best IPAs!",
    "tagLine": "Lead Android Engineer @ Aircall",
    "profilePicture": "https://sessionize.com/image/7c2f-400o400o2-Qf5YU6fWEKj4f9iBQP7Pcs.jpg",
    "sessions": [
      {
        "id": 301353,
        "name": "Building reliable web services with Kotlin Ktor"
      },
      {
        "id": 301250,
        "name": "Jetpack Compose: UI toolkit for Android and Desktop apps"
      }
    ],
    "isTopSpeaker": false,
    "links": [
      {
        "title": "Twitter",
        "url": "https://twitter.com/JulienSalvi",
        "linkType": "Twitter"
      },
      {
        "title": "LinkedIn",
        "url": "https://www.linkedin.com/in/salvijulien/",
        "linkType": "LinkedIn"
      },
      {
        "title": "Company Website",
        "url": "https://aircall.io/",
        "linkType": "Company_Website"
      }
    ],
    "questionAnswers": [],
    "categories": []
  },
  {
    "id": "608599c6-0472-4a70-b24b-38b0b7d74c90",
    "firstName": "Kaneez Fatima",
    "lastName": "Jowaheer",
    "fullName": "Kaneez Fatima Jowaheer",
    "bio": "I am Kaneez Fatima Jowaheer, currently a Consultant at Spoon Consulting Ltd. I am the Google Developer Student Club for the University of Mauritius Mentor and the Google Women Techmakers Ambassador for Mauritius. I am also a Tableau CRM Analytics Ambassador and a public speaker.",
    "tagLine": "University of Mauritius Student, Women Techmakers Mauritius Ambassador, Google Developer Student Club for the University of Mauritius Mentor,  Intern System Engineer at Harel Mallac Technologies Ltd",
    "profilePicture": "https://sessionize.com/image/87e7-400o400o2-fTgYa6zeMj1tRAZHpSvhAq.jpeg",
    "sessions": [
      {
        "id": 299982,
        "name": "How Artificial Intelligence is being used in NLP"
      }
    ],
    "isTopSpeaker": false,
    "links": [
      {
        "title": "LinkedIn",
        "url": "https://www.linkedin.com/in/kaneez-fatima-jowaheer-0928341a5/",
        "linkType": "LinkedIn"
      }
    ],
    "questionAnswers": [],
    "categories": []
  },
  {
    "id": "ef936d36-a1bc-4cd3-81c5-cacb3d29ce52",
    "firstName": "Kendall",
    "lastName": "Tang",
    "fullName": "Kendall Tang",
    "bio": "Passionate about IT, automation, renewable energies. Chairman of the Energy Efficiency Management Office. Kendall is also the CEO of RT Knits and Teamonite. He is continuously exploring and implementing new strategies to transform the industrial sector towards 4.0 ",
    "tagLine": "The unconventional CEO",
    "profilePicture": "https://sessionize.com/image/7caf-400o400o2-sEx9bcDF3vqdHMiF4dhKV8.jpg",
    "sessions": [
      {
        "id": 306269,
        "name": "Putting AI into action in Manufacturing"
      }
    ],
    "isTopSpeaker": false,
    "links": [
      {
        "title": "LinkedIn",
        "url": "https://www.linkedin.com/in/kendall-tang-3778ab6/",
        "linkType": "LinkedIn"
      }
    ],
    "questionAnswers": [],
    "categories": []
  },
  {
    "id": "4f850d61-b54a-4e83-895b-043292dd29d3",
    "firstName": "Kenneth",
    "lastName": "Christiansen",
    "fullName": "Kenneth Christiansen",
    "bio": "Kenneth Rohde Christiansen is a Danish software engineer and architect, specialized in mobile and web technology. Working at Intel out of Copenhagen, Kenneth helps define Intel’s strategy and plans regarding the Web Platform, as well as puts it into action.\r\n\r\nBefore joining Intel, Kenneth was employed by Nokia (Denmark and Brazil) where he worked on the Nokia N9 web browser, Qt, WebKit, as well as many other mobile projects. Kenneth is an elected member of the W3C Technical Architect Group (TAG).\r\n\r\nCurrently working on extending Progressive Web Apps with more native capabilities as part of Project Fugu\r\n",
    "tagLine": "Web Platform Architect and Principal Engineer at Intel Corporation,  W3C Technical Architecture Group alumni",
    "profilePicture": "https://sessionize.com/image/3863-400o400o2-61-b54a-4e83-895b-043292dd29d3.89ecda2e-523f-40f7-a2a8-90b38c85864b.jpg",
    "sessions": [
      {
        "id": 292530,
        "name": "Beyond the web of today"
      },
      {
        "id": 292000,
        "name": "Making the web the application platform of the future"
      }
    ],
    "isTopSpeaker": false,
    "links": [
      {
        "title": "Twitter",
        "url": "https://twitter.com/kennethrohde",
        "linkType": "Twitter"
      },
      {
        "title": "LinkedIn",
        "url": "https://www.linkedin.com/in/kenneth-rohde-christiansen/",
        "linkType": "LinkedIn"
      },
      {
        "title": "Company Website",
        "url": "https://intel.com",
        "linkType": "Company_Website"
      }
    ],
    "questionAnswers": [],
    "categories": []
  },
  {
    "id": "79196cc1-32fa-4ce8-8204-7aba4c84e9ce",
    "firstName": "Kushul",
    "lastName": "Soomaree",
    "fullName": "Kushul Soomaree",
    "bio": "Senior Front End Engineer @ Prodigious | Web Accessibility | UI/UX expert | Vuejs | TailwindCSS | Drupal9 |  Webcup & krakathon winner | Certified Trainer | Webcup & Digicup 2022 Jury",
    "tagLine": "Senior Front End Engineer, Prodigious Ltd",
    "profilePicture": "https://sessionize.com/image/d64e-400o400o2-BGeDEmctuLRuPRLN7WmCkF.jpg",
    "sessions": [
      {
        "id": 293915,
        "name": "Ghost theme development"
      }
    ],
    "isTopSpeaker": false,
    "links": [
      {
        "title": "Twitter",
        "url": "https://twitter.com/kushul_soomaree",
        "linkType": "Twitter"
      },
      {
        "title": "LinkedIn",
        "url": "https://www.linkedin.com/in/kushul-soomaree-515502147",
        "linkType": "LinkedIn"
      },
      {
        "title": "Blog",
        "url": "https://kushulsoomaree.netlify.com/",
        "linkType": "Blog"
      },
      {
        "title": "Company Website",
        "url": "https://kushulsoomaree.netlify.com",
        "linkType": "Company_Website"
      }
    ],
    "questionAnswers": [],
    "categories": []
  },
  {
    "id": "a52fead5-fedc-48da-94bf-192f1c171681",
    "firstName": "Loic",
    "lastName": "Forget",
    "fullName": "Loic Forget",
    "bio": "The biggest geek in Mauritius (literally)!! Loïc goes against the evil forces of traditionalists to save the island & protect nerd-castle La Sentinelle.",
    "tagLine": "La Sentinelle Ltd",
    "profilePicture": "https://sessionize.com/image/bfa1-400o400o2-RRQJkgoYQgajvyW7ztD6aS.jpg",
    "sessions": [
      {
        "id": 372620,
        "name": "Right to Repair Much?"
      }
    ],
    "isTopSpeaker": false,
    "links": [
      {
        "title": "Twitter",
        "url": "https://twitter.com/kou1ack",
        "linkType": "Twitter"
      },
      {
        "title": "LinkedIn",
        "url": "https://linkedin.com/in/aimelavideo/",
        "linkType": "LinkedIn"
      },
      {
        "title": "Instagram",
        "url": "https://www.instagram.com/boycriedwoof/",
        "linkType": "Instagram"
      },
      {
        "title": "Blog",
        "url": "https://linktr.ee/Be1Mari",
        "linkType": "Blog"
      },
      {
        "title": "Company Website",
        "url": "https://www.lasentinelle.mu",
        "linkType": "Company_Website"
      }
    ],
    "questionAnswers": [],
    "categories": []
  },
  {
    "id": "336671e4-3f17-4dbe-ab1c-20a8b38cc1a5",
    "firstName": "Lovelesh",
    "lastName": "Beeharry",
    "fullName": "Lovelesh Beeharry",
    "bio": "- Founder and President of MSTQB\r\n- Lead Automation Test Engineer at iQera IO\r\n- International Conference Speaker & Moderator\r\n- CommonWealth Executive MBA\r\n- Bachelor of Engineering (Computer Science)\r\n- 12 years of experience in software testing\r\n- Experienced in manual testing, automation testing & performance testing.\r\n- Experience automation testing framework development.\r\n- ISTQB® Trainer",
    "tagLine": "President of Mauritian Software Testing Qualification Board",
    "profilePicture": "https://sessionize.com/image/e56e-400o400o2-Bzv7mGMGBS9d5xoudUGWSP.png",
    "sessions": [
      {
        "id": 297940,
        "name": "The Mathematics of Performance Testing"
      }
    ],
    "isTopSpeaker": false,
    "links": [
      {
        "title": "LinkedIn",
        "url": "https://www.linkedin.com/in/lovelesh-beeharry/",
        "linkType": "LinkedIn"
      }
    ],
    "questionAnswers": [],
    "categories": []
  },
  {
    "id": "4dc79966-a989-45ff-b2e7-6b6f3a5433d0",
    "firstName": "Mahima",
    "lastName": "Ramgolam",
    "fullName": "Mahima Ramgolam",
    "bio": "In the process to become a good and cool developer!",
    "tagLine": "Frontend Developer",
    "profilePicture": "https://sessionize.com/image/315d-400o400o2-sJovvAB5HY9YX16jf7fYjb.jpg",
    "sessions": [
      {
        "id": 302788,
        "name": "An introduction to TailwindCSS"
      }
    ],
    "isTopSpeaker": false,
    "links": [
      {
        "title": "LinkedIn",
        "url": "https://www.linkedin.com/in/mahima-ramgolam-240572138",
        "linkType": "LinkedIn"
      },
      {
        "title": "Blog",
        "url": "https://mahima.ramgolam.com",
        "linkType": "Blog"
      }
    ],
    "questionAnswers": [],
    "categories": []
  },
  {
    "id": "83a70482-4c89-47ea-b79e-4e069ad27cf9",
    "firstName": "Mateusz",
    "lastName": "Kleczkowski",
    "fullName": "Mateusz Kleczkowski",
    "bio": "Mateusz is a Technical Architect at Objectivity with 6+ years of professional experience. He’s an expert in web application development, with expertise in ASP.NET backend services and Azure Cloud Architecture. He has gained his experience working in retail, accounting and aviation industry, on many various projects, including a highly available ecommerce platform used by millions of users daily. \r\n\r\nFor the last 3 years, he has worked on bespoke CMS-based projects what allowed him to learn the methodology of working with a CMS and the ins and outs of Umbraco. Despite his initial doubts regarding these systems, he now has a great appreciation of the significant value they can bring to projects at a very low cost. \r\n\r\nMateusz is an always smiling, passionate person, who loves sharing his knowledge with lots of positive energy. He’s going to be extremely happy to see you at the event!\r\n",
    "tagLine": "Technical Architect at Objectivity",
    "profilePicture": "https://sessionize.com/image/3ae9-400o400o2-SCaJYJyvyhACXiF5uVNW2k.jpg",
    "sessions": [
      {
        "id": 309955,
        "name": "Take what’s given, use it however you need. Get to know Umbraco CMS."
      }
    ],
    "isTopSpeaker": false,
    "links": [
      {
        "title": "LinkedIn",
        "url": "https://www.linkedin.com/in/mkleczkowski",
        "linkType": "LinkedIn"
      }
    ],
    "questionAnswers": [],
    "categories": []
  },
  {
    "id": "c6290cf3-c046-41b7-9f5f-d47d05c55baf",
    "firstName": "Mervyn",
    "lastName": "Manilall",
    "fullName": "Mervyn Manilall",
    "bio": "- Graduated in computer science and started freelance web development  in 2016\r\n\r\n- Data engineer at The Cloud Factory EMEA from 2016 - 2017\r\n\r\n- Specialist in Information System at Orange Business Service 2017- 2019\r\n\r\n- Software engineer at MCB 2019 - present",
    "tagLine": "Software engineer - MCB",
    "profilePicture": "https://sessionize.com/image/1709-400o400o2-aHuirEvMFut4hP9hGukHTL.jpg",
    "sessions": [
      {
        "id": 407127,
        "name": "Add more security with Azure Keyvault."
      }
    ],
    "isTopSpeaker": false,
    "links": [
      {
        "title": "Twitter",
        "url": "https://twitter.com/MervynManilall",
        "linkType": "Twitter"
      },
      {
        "title": "LinkedIn",
        "url": "https://www.linkedin.com/in/mervyn-manilall/",
        "linkType": "LinkedIn"
      },
      {
        "title": "Blog",
        "url": "https://mervyn-manilall.medium.com/",
        "linkType": "Blog"
      }
    ],
    "questionAnswers": [],
    "categories": []
  },
  {
    "id": "7c65fbc3-4a09-447f-b9b9-e9f28f32218b",
    "firstName": "Mohamed ",
    "lastName": "Edun",
    "fullName": "Mohamed Edun",
    "bio": "Javascript Mechanic",
    "tagLine": "Providus - Senior Developer",
    "profilePicture": "https://sessionize.com/image/904d-400o400o2-MJ1pMbzYBEsN2esRNv4qKV.jpg",
    "sessions": [
      {
        "id": 385704,
        "name": "Javascript: A look behind the scenes"
      }
    ],
    "isTopSpeaker": false,
    "links": [
      {
        "title": "LinkedIn",
        "url": "https://www.linkedin.com/in/moedun/",
        "linkType": "LinkedIn"
      }
    ],
    "questionAnswers": [],
    "categories": []
  },
  {
    "id": "c0e8efcc-ef98-4c67-bc36-3b5e94034ced",
    "firstName": "Mohand",
    "lastName": "FERHI",
    "fullName": "Mohand FERHI",
    "bio": "Passionné par la technologie et le management de l'humain et des organisations.\r\nJ'aime travailler dans un contexte avec de gros challenges comme accompagner les entreprises à assurer une croissance forte, rendre scalables et performantes des applications, très orienté \"problem solving\".\r\nConvaincu que la #persévérance, l'#agilité et l'#amélioration #continue sont les clés du succès.",
    "tagLine": "Iqera, CTO",
    "profilePicture": "https://sessionize.com/image/1c70-400o400o2-3tnxFbQwNmvR3A6coLrwXt.jfif",
    "sessions": [
      {
        "id": 302404,
        "name": "Low-code et architecture micro service"
      }
    ],
    "isTopSpeaker": false,
    "links": [
      {
        "title": "Twitter",
        "url": "https://twitter.com/",
        "linkType": "Twitter"
      },
      {
        "title": "LinkedIn",
        "url": "https://www.linkedin.com/in/mohand-ferhi-46293713b/",
        "linkType": "LinkedIn"
      },
      {
        "title": "Blog",
        "url": "https://www.linkedin.com/in/mohand-ferhi-46293713b/",
        "linkType": "Blog"
      }
    ],
    "questionAnswers": [],
    "categories": []
  },
  {
    "id": "6b6eaf16-e715-4dab-8fa8-60f8281e3269",
    "firstName": "Muhammad Yusuf",
    "lastName": "Abdool Satar",
    "fullName": "Muhammad Yusuf Abdool Satar",
    "bio": "Software Engineer",
    "tagLine": "Vitae Non Scholae Discendum",
    "profilePicture": "https://sessionize.com/image/68d3-400o400o2-WafCdjvguHrH2Pi8WV1xYq.png",
    "sessions": [
      {
        "id": 303280,
        "name": "Go: from scratch to prod"
      }
    ],
    "isTopSpeaker": false,
    "links": [
      {
        "title": "Twitter",
        "url": "https://twitter.com/__fluxy__",
        "linkType": "Twitter"
      },
      {
        "title": "LinkedIn",
        "url": "https://www.linkedin.com/in/fluxy/",
        "linkType": "LinkedIn"
      },
      {
        "title": "Blog",
        "url": "https://fluxy.net",
        "linkType": "Blog"
      }
    ],
    "questionAnswers": [],
    "categories": []
  },
  {
    "id": "e4d51ad0-51f7-44bc-ade2-8c7250bb5400",
    "firstName": "Nathan",
    "lastName": "Mangar",
    "fullName": "Nathan Mangar",
    "bio": "Nathan is a guy that loves anything code and hardware related. His company Thundergear Technologies LTD aka thundergear.io specializes in open hardware, print-on-demand and e-commerce solutions.",
    "tagLine": "Director of thundergear.io",
    "profilePicture": "https://sessionize.com/image/ed87-400o400o2-4iSHd7CawHBUQZpfFCb5yv.jpg",
    "sessions": [
      {
        "id": 290556,
        "name": "How to certify your hardware project or product by OSHWA (Open Source Hardware Association)"
      },
      {
        "id": 290557,
        "name": "Printed Circuit Board design and manufacturing"
      }
    ],
    "isTopSpeaker": false,
    "links": [
      {
        "title": "Twitter",
        "url": "https://twitter.com/atech5122",
        "linkType": "Twitter"
      },
      {
        "title": "LinkedIn",
        "url": "https://mu.linkedin.com/in/nathan-sunil-mangar-a43283133",
        "linkType": "LinkedIn"
      },
      {
        "title": "Company Website",
        "url": "https://thundergear.io",
        "linkType": "Company_Website"
      }
    ],
    "questionAnswers": [],
    "categories": []
  },
  {
    "id": "330d0193-0f5f-4f9a-9df1-741448fa390d",
    "firstName": "Nayar",
    "lastName": "Joolfoo",
    "fullName": "Nayar Joolfoo",
    "bio": "Who else loves Hiking?",
    "tagLine": "Freelance Consultant / DevOps ",
    "profilePicture": "https://sessionize.com/image/9bb3-400o400o2-93-0f5f-4f9a-9df1-741448fa390d.878b26b0-903d-4b4e-85b1-3545cccd8069.jpg",
    "sessions": [
      {
        "id": 302568,
        "name": "My First Baby Steps with: Git"
      },
      {
        "id": 302569,
        "name": "IoT and social media integration with Node-RED"
      }
    ],
    "isTopSpeaker": false,
    "links": [
      {
        "title": "Blog",
        "url": "https://nayarweb.com/blog/",
        "linkType": "Blog"
      }
    ],
    "questionAnswers": [],
    "categories": []
  },
  {
    "id": "3a68cb63-d151-41e7-92d7-720bc6a191b7",
    "firstName": "Nirmala",
    "lastName": "Saneechur",
    "fullName": "Nirmala Saneechur",
    "bio": "Having over 16 years of experience in testing and a real passion for quality, I  enjoy coaching and mentoring others in this discipline. \r\n\r\nDuring my rich career, I have had the opportunity to get involved in functional as well as non functional testing. Quality is not just the responsibility of the test/QA team. It is up to each and everyone, who is involved in the project, to ensure that what we deliver meets or even exceeds the expectation of our clients.\r\n\r\nIn the past 5 years, I have been managing test teams. The key is in ensuring that every team member realises the importance of what we do - we are the guarantors of quality! Hence the need to keep ourselves up to date with the latest in the testing field and also having an indepth knowledge of the business in which we evolve.\r\n\r\nI am also an executive member MSTQB, the Mauritian chapter for ISTQB (International Software Testing Qualifications Board). Our objective is to grow and connect the software testing community in Mauritius. \r\n\r\n\r\n",
    "tagLine": "Test Manager at iQera IO",
    "profilePicture": "https://sessionize.com/image/5023-400o400o2-3ANSXePmGP2XsGWwzuCekG.jpg",
    "sessions": [
      {
        "id": 305220,
        "name": "Maintaining quality in the new normal"
      }
    ],
    "isTopSpeaker": false,
    "links": [
      {
        "title": "LinkedIn",
        "url": "https://www.linkedin.com/in/nirmala-saneechur-2303423",
        "linkType": "LinkedIn"
      }
    ],
    "questionAnswers": [],
    "categories": []
  },
  {
    "id": "84b950ee-81ab-4aea-a5f2-f8cda15a69e8",
    "firstName": "Nirvan",
    "lastName": "Pagooah",
    "fullName": "Nirvan Pagooah",
    "bio": "Tejas is an agile Engineering Manager with a strong focus on R&D, Scalability, Full Stack Engineering, and in crafting technology-agnostic systems. He is passionate about building things elegantly and at scale. He is currently directing technical strategies for globally-scaled technology projects at KLANIK (Mauritius) with the Digital Factory & HQ in Marseille. Tejas formerly led world-class projects with distributed teams across Mauritius, France, India & Madagascar and has comprehensive technical experience in DevOps culture, managing software development processes, infra design, leading teams, QA, and software delivery. \r\n\r\nHe is an also avid Open Source advocate & contributor.",
    "tagLine": "Engineering Manager @ KLANIK Mauritius",
    "profilePicture": "https://sessionize.com/image/3fb5-400o400o2-3YS9jLTpgtr9trijyeSMah.png",
    "sessions": [
      {
        "id": 302708,
        "name": "The Politics & Fallacies in Agile"
      },
      {
        "id": 302232,
        "name": "Purple People at the heart of tech companies"
      }
    ],
    "isTopSpeaker": false,
    "links": [
      {
        "title": "Twitter",
        "url": "https://www.twitter.com/nirvanpagooah",
        "linkType": "Twitter"
      },
      {
        "title": "LinkedIn",
        "url": "https://linkedin.com/in/tejaspagooah/",
        "linkType": "LinkedIn"
      },
      {
        "title": "Blog",
        "url": "http://blog.nirvan.pagooah.com",
        "linkType": "Blog"
      }
    ],
    "questionAnswers": [],
    "categories": []
  },
  {
    "id": "f72d6333-ba68-43df-be79-0e42c7162631",
    "firstName": "Om",
    "lastName": "Gokhool",
    "fullName": "Om Gokhool",
    "bio": "Experienced Solution Architect with a demonstrated history of working in the information technology and services industry. Skilled in Communication, Time Management, Teamwork, Research and Development (R&D), and Creative Problem Solving. Strong engineering professional with a Master's degree focused in Software Project Management from University of Mauritius. Currently working at Harel Mallac Technologies as a Solution Architect, developing digital solutions and managing projects.",
    "tagLine": "Harel Mallac Technologies, Solution Architect",
    "profilePicture": "https://sessionize.com/image/4425-400o400o2-dfQXbQxX7WWJuWeB6JpHL.jpg",
    "sessions": [
      {
        "id": 302794,
        "name": "Re - Engineering the Digitalization Process"
      }
    ],
    "isTopSpeaker": false,
    "links": [
      {
        "title": "Twitter",
        "url": "https://twitter.com/omgokhool",
        "linkType": "Twitter"
      },
      {
        "title": "LinkedIn",
        "url": "https://www.linkedin.com/in/omdeep-gokhool-75b66b167/",
        "linkType": "LinkedIn"
      },
      {
        "title": "Blog",
        "url": "https://omgokhool.com/",
        "linkType": "Blog"
      }
    ],
    "questionAnswers": [],
    "categories": []
  },
  {
    "id": "51f713e3-f67b-4884-aed0-ef782fda8a6c",
    "firstName": "Purdaseea",
    "lastName": "Dhaneshwursingh",
    "fullName": "Purdaseea Dhaneshwursingh",
    "bio": "Let's Automate everything",
    "tagLine": "Lead DevOps Engineer at  SD Worx Mauritius",
    "profilePicture": "https://sessionize.com/image/d1f8-400o400o2-e3-f67b-4884-aed0-ef782fda8a6c.3f86d5b7-4b87-47e4-b2a7-b461a4a5978a.jpg",
    "sessions": [
      {
        "id": 289928,
        "name": "Microsoft genomics"
      }
    ],
    "isTopSpeaker": false,
    "links": [],
    "questionAnswers": [],
    "categories": []
  },
  {
    "id": "146ba683-b905-46a9-bc61-108c46964ce8",
    "firstName": "Renghen",
    "lastName": "Thanos",
    "fullName": "Renghen Thanos",
    "bio": "Been doing software dev since 1990",
    "tagLine": "I do not do tagline",
    "profilePicture": "https://sessionize.com/image/3473-400o400o2-83-b905-46a9-bc61-108c46964ce8.c2a2c4ad-327b-44a5-a4ea-99fe8e86d59b.jpg",
    "sessions": [
      {
        "id": 302708,
        "name": "The Politics & Fallacies in Agile"
      },
      {
        "id": 290724,
        "name": "Types to the rescue"
      }
    ],
    "isTopSpeaker": false,
    "links": [
      {
        "title": "LinkedIn",
        "url": "https://www.linkedin.com/in/renghen-pajanilingum-7406374/",
        "linkType": "LinkedIn"
      }
    ],
    "questionAnswers": [],
    "categories": []
  },
  {
    "id": "9b215c5f-e775-4470-9473-1295c638cbce",
    "firstName": "Riad ",
    "lastName": "Mohamudally",
    "fullName": "Riad Mohamudally",
    "bio": "Riad is an IT professional with more than 23 years of experience in the field of ICT promotion and training, IT Infrastructure. \r\n\r\nHe holds a BSc in Computer Science. He currently works in the capacity of Business Analyst of the Planning Research and Development section at the National Computer Board.\r\n\r\nHe is involved in several projects such as Open Source, GIS system. He is currently a lead member on the National IoT Platform project.",
    "tagLine": "Business Analyst National Computer Board",
    "profilePicture": "https://sessionize.com/image/3c30-400o400o2-sXz44y2ZZNFeFovjwcMULs.png",
    "sessions": [
      {
        "id": 389176,
        "name": "National Geo and IOT Portals  and Mobile Applications"
      }
    ],
    "isTopSpeaker": false,
    "links": [],
    "questionAnswers": [],
    "categories": []
  },
  {
    "id": "2e82117a-6798-4e3f-a78d-b547047d02ff",
    "firstName": "Rishi",
    "lastName": "Abeeluck",
    "fullName": "Rishi Abeeluck",
    "bio": "Rishi is an experienced Software Engineer with a demonstrated history of working in the broadcast media industry, finance industry & retail sector. Skilled in Full Stack Web Development, Software Development and Agile Project Management. Recently delivered a challenging project for the transportation industry and currently working on a project for the education sector.",
    "tagLine": "ELCA | Senior Software Engineer",
    "profilePicture": "https://sessionize.com/image/9380-400o400o2-7a-6798-4e3f-a78d-b547047d02ff.3ce94510-2c18-404b-8d05-85c54be8191c.jpg",
    "sessions": [
      {
        "id": 302782,
        "name": "Blockchain in a Nutshell"
      },
      {
        "id": 302813,
        "name": "Stacks for Web Applications"
      }
    ],
    "isTopSpeaker": false,
    "links": [],
    "questionAnswers": [],
    "categories": []
  },
  {
    "id": "dbc1be6b-eb43-4569-be8e-5c6cdabfc107",
    "firstName": "Saamiyah",
    "lastName": "Peerun",
    "fullName": "Saamiyah Peerun",
    "bio": "React Developer - TeamEngine",
    "tagLine": "Performs devcrafts by invoking functions on a daily basis",
    "profilePicture": "https://sessionize.com/image/bf54-400o400o2-6b-eb43-4569-be8e-5c6cdabfc107.ffe67ed9-3071-461e-9595-b19e8fd0ca29.jpg",
    "sessions": [
      {
        "id": 302659,
        "name": "Debugging techniques for uncertain times"
      }
    ],
    "isTopSpeaker": false,
    "links": [
      {
        "title": "Twitter",
        "url": "https://twitter.com/smearthelove",
        "linkType": "Twitter"
      },
      {
        "title": "LinkedIn",
        "url": "https://www.linkedin.com/in/saamiyah-peerun-9a9507a3/",
        "linkType": "LinkedIn"
      },
      {
        "title": "Blog",
        "url": "http://saamiyah.dev",
        "linkType": "Blog"
      }
    ],
    "questionAnswers": [],
    "categories": []
  },
  {
    "id": "cbf5680a-86ca-48f9-8450-a8ce86aca4f9",
    "firstName": "Sadhveer Sharma (Yudish)",
    "lastName": "Luchmun",
    "fullName": "Sadhveer Sharma (Yudish) Luchmun",
    "bio": "I am an IT professional engaging in software development and infrastructure, mostly focused on Microsoft technologies. ",
    "tagLine": "Lead Software Developer",
    "profilePicture": "https://sessionize.com/image/0a41-400o400o2-0a-86ca-48f9-8450-a8ce86aca4f9.301a9d0f-fb2f-4b82-865a-4d70b9d88500.jpg",
    "sessions": [
      {
        "id": 302781,
        "name": "Build Applications Fast, Right, and for the Future with Outsystems"
      }
    ],
    "isTopSpeaker": false,
    "links": [
      {
        "title": "Twitter",
        "url": "https://twitter.com/ssyluchmun",
        "linkType": "Twitter"
      },
      {
        "title": "LinkedIn",
        "url": "https://mu.linkedin.com/in/ssyluchmun",
        "linkType": "LinkedIn"
      }
    ],
    "questionAnswers": [],
    "categories": []
  },
  {
    "id": "d802c569-2764-4a8c-ac90-4dec8e3c3f41",
    "firstName": "Sandeep",
    "lastName": "Ramgolam",
    "fullName": "Sandeep Ramgolam",
    "bio": "Frontend | UX | Linux | OpenSource\r\nWrites HTML for a living\r\n\r\n",
    "tagLine": "Senior Front-End Developer, Atellio",
    "profilePicture": "https://sessionize.com/image/ff39-400o400o2-69-2764-4a8c-ac90-4dec8e3c3f41.a10c0351-7345-4259-9902-6f712df27aec.JPG",
    "sessions": [
      {
        "id": 302541,
        "name": "Modern Front-end Development with ViteJS"
      },
      {
        "id": 302537,
        "name": "Lightning Talks 2022"
      }
    ],
    "isTopSpeaker": false,
    "links": [
      {
        "title": "Twitter",
        "url": "https://www.twitter.com/__sun__",
        "linkType": "Twitter"
      },
      {
        "title": "LinkedIn",
        "url": "https://www.linkedin.com/in/sandeepramgolam/",
        "linkType": "LinkedIn"
      },
      {
        "title": "Blog",
        "url": "https://sandeep.ramgolam.com",
        "linkType": "Blog"
      }
    ],
    "questionAnswers": [],
    "categories": []
  },
  {
    "id": "a13ef284-cbaa-48ad-a74d-cb11922dd895",
    "firstName": "Shaan",
    "lastName": "Nobee",
    "fullName": "Shaan Nobee",
    "bio": "Shaan is a software engineer at EventStore, the company that builds EventStoreDB - an open source database engine for event sourcing.\r\n\r\nHis main interests include programming, algorithms, computer security and distributed systems.",
    "tagLine": "Software Engineer at EventStore",
    "profilePicture": "https://sessionize.com/image/dc2e-400o400o2-84-cbaa-48ad-a74d-cb11922dd895.b143b8f0-be91-4b84-88b8-2f31a444b98d.jpg",
    "sessions": [
      {
        "id": 302421,
        "name": "How I ended up needing to fix a bug in the ZFS file system"
      },
      {
        "id": 298382,
        "name": "Remote code execution - how security exploits work"
      }
    ],
    "isTopSpeaker": false,
    "links": [
      {
        "title": "LinkedIn",
        "url": "https://www.linkedin.com/in/shaan-nobee-97036bbb/",
        "linkType": "LinkedIn"
      }
    ],
    "questionAnswers": [],
    "categories": []
  },
  {
    "id": "e7063218-bdb2-47fd-a0f2-2c9a1129a97b",
    "firstName": "Sharfaraaz",
    "lastName": "Lauthan",
    "fullName": "Sharfaraaz Lauthan",
    "bio": "Ceridian Data Intelligence Developer ",
    "tagLine": "Ceridian Data Intelligence Developer ",
    "profilePicture": "https://sessionize.com/image/f4bf-400o400o2-GDrt295Yne2YZbG1XSXUNq.png",
    "sessions": [
      {
        "id": 383724,
        "name": "Data Analytics"
      }
    ],
    "isTopSpeaker": false,
    "links": [],
    "questionAnswers": [],
    "categories": []
  },
  {
    "id": "81cb3983-21be-40b3-977e-f874acae48ff",
    "firstName": "Shelly",
    "lastName": "Pursooramen",
    "fullName": "Shelly Pursooramen",
    "bio": "With over 6 years experience in the IT industry. Shelly has been working along with IT professional on a day to day basis.\r\nBeing a non-technical person in this technical world, allowed her to look at this industry from a different angle realizing the importance of wellbeing at work and how it can drastically impact on productivity.",
    "tagLine": "Marketing & Communication Executive, ServiQual",
    "profilePicture": "https://sessionize.com/image/a2d8-400o400o2-RKTDMEVgCphizmnSLU6Eyu.jpg",
    "sessions": [
      {
        "id": 290469,
        "name": "Your Happiness & Wellbeing Matters."
      }
    ],
    "isTopSpeaker": false,
    "links": [
      {
        "title": "LinkedIn",
        "url": "https://www.linkedin.com/in/shelly-pursooramen-6b52728a/",
        "linkType": "LinkedIn"
      }
    ],
    "questionAnswers": [],
    "categories": []
  },
  {
    "id": "d1a5d8cb-8e83-4cad-97fc-beb329206346",
    "firstName": "Sibella",
    "lastName": "Arlanda",
    "fullName": "Sibella Arlanda",
    "bio": "Polymathic individual, Translator and Transcriber, Aspiring Sociologist.",
    "tagLine": "Translator ",
    "profilePicture": "https://sessionize.com/image/324b-400o400o2-acbi9xY6WmcVTezobX6EKY.jpg",
    "sessions": [
      {
        "id": 302835,
        "name": "\"Imaginative Art\" for a living"
      }
    ],
    "isTopSpeaker": false,
    "links": [
      {
        "title": "LinkedIn",
        "url": "https://www.linkedin.com/in/sibella-arlanda",
        "linkType": "LinkedIn"
      }
    ],
    "questionAnswers": [],
    "categories": []
  },
  {
    "id": "5ca04941-04c9-4ad4-80f3-081108358418",
    "firstName": "Soodeshna",
    "lastName": "Bappoo",
    "fullName": "Soodeshna Bappoo",
    "bio": "Software Developer at Maureva Ltd",
    "tagLine": "Software Developer - Maureva Ltd",
    "profilePicture": "https://sessionize.com/image/129b-400o400o2-fcCDzy7RVE98i8yf5m9ekh.jpg",
    "sessions": [
      {
        "id": 302586,
        "name": "Encryption in AWS"
      }
    ],
    "isTopSpeaker": false,
    "links": [
      {
        "title": "LinkedIn",
        "url": "https://www.linkedin.com/in/soodeshna-bappoo",
        "linkType": "LinkedIn"
      }
    ],
    "questionAnswers": [],
    "categories": []
  },
  {
    "id": "b4b8eaff-c563-48b1-9d56-a4b7f91f7720",
    "firstName": "Stefan",
    "lastName": "Wong Ng",
    "fullName": "Stefan Wong Ng",
    "bio": "Cosplayer since 2010",
    "tagLine": "CosmauCon Cosplayer",
    "profilePicture": "https://sessionize.com/image/1a71-400o400o2-Mfh4QsmpkFhp7FucgnT3PN.JPG",
    "sessions": [
      {
        "id": 314339,
        "name": "Cosplay"
      }
    ],
    "isTopSpeaker": false,
    "links": [],
    "questionAnswers": [],
    "categories": []
  },
  {
    "id": "2bc1b315-b478-41ce-a8de-527037549664",
    "firstName": "Sujit",
    "lastName": "Woozageer",
    "fullName": "Sujit Woozageer",
    "bio": "Sujit Woozageer, is a Business Transformation Professional with over 30 years of experience at higher management level across various industries ranging from Textiles, Medical Insurance Administration, Insurance Broking, BPO, Healthcare and Insurance. His focus has been on driving Business Transformation, Digitalisation, Process Reengineering, Efficiency, Data Analytics and Innovation. \r\n\r\nSujit started his career in the early 90s in the textile industry as Head of IT before moving to other managerial roles to become the Operations Manager at Momentum Ltd., then at Medscheme Ltd. He was later promoted to General Manager and to finally be appointed as Managing Director of Medscheme (Mtius) Ltd., Medscheme International Ltd. & Afrocentric International Ltd., all headquartered in South Africa. He assumed the latter role for 6 years before accepting the position of Chief Officer: Shared Services & Innovation at C-Care Ltd. He joined Swan in February 2021 as a Digital Transformation Consultant and was appointed as Senior Manager Business Transformation and Solutions in March 2022.\r\n",
    "tagLine": "Change before you have to.",
    "profilePicture": "https://sessionize.com/image/11de-400o400o2-aXRz72uMWmpQ729tomnHAq.jpg",
    "sessions": [
      {
        "id": 385121,
        "name": "SWAN - The Digital Journey"
      }
    ],
    "isTopSpeaker": false,
    "links": [
      {
        "title": "LinkedIn",
        "url": "https://www.linkedin.com/in/sujit-woozageer-57b151114",
        "linkType": "LinkedIn"
      }
    ],
    "questionAnswers": [],
    "categories": []
  },
  {
    "id": "9a95d0ba-6acd-47ba-af75-d0d2676d9276",
    "firstName": "Suyash",
    "lastName": "Sumaroo",
    "fullName": "Suyash Sumaroo",
    "bio": "Suyash has helped in setting up projects and businesses including Codevigor (a startup specialized in the development of blockchain applications), Horizon Africa (a blockchain focused on NFTs and Metaverses), StoragePlus (the first commercial Blockchain Application in Mauritius), Loot NFT (an international NFT Metaverse project) and many other businesses in the last 8 years.",
    "tagLine": "Serial Blockchain Entrepreneur",
    "profilePicture": "https://sessionize.com/image/d084-400o400o2-3rpxysv6v8QuxNgNbmNcSS.png",
    "sessions": [
      {
        "id": 290493,
        "name": "NFT - The future of finance"
      }
    ],
    "isTopSpeaker": false,
    "links": [
      {
        "title": "Twitter",
        "url": "https://twitter.com/suyash515",
        "linkType": "Twitter"
      },
      {
        "title": "LinkedIn",
        "url": "https://www.linkedin.com/in/suyashsumaroo/",
        "linkType": "LinkedIn"
      },
      {
        "title": "Facebook",
        "url": "https://www.facebook.com/suyash.sumaroo.the.entrepreneur",
        "linkType": "Facebook"
      },
      {
        "title": "Blog",
        "url": "https://suyashsumaroo.medium.com/",
        "linkType": "Blog"
      },
      {
        "title": "Company Website",
        "url": "https://www.codevigor.com",
        "linkType": "Company_Website"
      }
    ],
    "questionAnswers": [],
    "categories": []
  },
  {
    "id": "9e81e32f-b831-4f64-969b-3fefc3ef1dc8",
    "firstName": "Tarounen",
    "lastName": ".",
    "fullName": "Tarounen .",
    "bio": "Just a curious developer trying to keep up to date with the latest trend in the programming and digital world and not breaking working code!",
    "tagLine": "Software Developer at Providus, Geek",
    "profilePicture": "https://sessionize.com/image/422d-400o400o2-DVG6xTEQPi6RtSeKfnk1km.jpg",
    "sessions": [
      {
        "id": 385705,
        "name": "Asset tokenization on Algorand Blockchain"
      }
    ],
    "isTopSpeaker": false,
    "links": [
      {
        "title": "Twitter",
        "url": "https://twitter.com/tarounen",
        "linkType": "Twitter"
      },
      {
        "title": "LinkedIn",
        "url": "https://linkedin.com/in/rundenmonique",
        "linkType": "LinkedIn"
      }
    ],
    "questionAnswers": [],
    "categories": []
  },
  {
    "id": "1ad5cb40-0f33-4b33-ab8d-415a5febf690",
    "firstName": "Vanessa",
    "lastName": "V.Chellen ",
    "fullName": "Vanessa V.Chellen",
    "bio": "Directeur technique chez Extension Interactive. J’habite l’univers PHP depuis 14 ans et l’ai suivi/soutenu dans son évolution de PHP 4 à maintenant...  Spécialisé sur Symfony, Drupal et Prestashop, j’adore partager ma passion du code autour de moi.",
    "tagLine": "CTO, Extension Interactive",
    "profilePicture": "https://sessionize.com/image/c509-400o400o2-9CUD7AGNW8bCgU1aVHzkXC.jpg",
    "sessions": [
      {
        "id": 292225,
        "name": "Symfony - Workshop"
      }
    ],
    "isTopSpeaker": false,
    "links": [
      {
        "title": "Twitter",
        "url": "https://twitter.com/VanessaChellen",
        "linkType": "Twitter"
      },
      {
        "title": "LinkedIn",
        "url": "https://www.linkedin.com/in/vanessa-v-chellen-a8ab3125/",
        "linkType": "LinkedIn"
      },
      {
        "title": "Blog",
        "url": "https://twitter.com/VanessaChellen",
        "linkType": "Blog"
      }
    ],
    "questionAnswers": [],
    "categories": []
  },
  {
    "id": "cf415be6-0558-4411-aa4d-dee4f0648547",
    "firstName": "Vidush H.",
    "lastName": "Namah",
    "fullName": "Vidush H. Namah",
    "bio": "He is a nomad of the geek world - traveling through various technologies yet never settling. He also writes really dramatic biographies.",
    "tagLine": "School of Coding, Witchcraft and Wizardry",
    "profilePicture": "https://sessionize.com/image/12b7-400o400o2-MKq327CHjiDkGp5Gj6WYRo.png",
    "sessions": [
      {
        "id": 302766,
        "name": "3D Websites: Three.JS"
      },
      {
        "id": 302779,
        "name": "The Story Behind Freelancing"
      }
    ],
    "isTopSpeaker": false,
    "links": [
      {
        "title": "Twitter",
        "url": "https://twitter.com/VHNamah",
        "linkType": "Twitter"
      },
      {
        "title": "LinkedIn",
        "url": "https://www.linkedin.com/in/vnamah/",
        "linkType": "LinkedIn"
      },
      {
        "title": "Blog",
        "url": "https://vnsnippets.github.io",
        "linkType": "Blog"
      }
    ],
    "questionAnswers": [],
    "categories": []
  },
  {
    "id": "58202e68-8dd8-44ff-bd90-d354df607627",
    "firstName": "Vincent",
    "lastName": "Chatard",
    "fullName": "Vincent Chatard",
    "bio": "Vincent was appointed Chief Operating Officer in September 2015 and since February 2018, he is also steering the Digital Transformation Programme. He has accumulated wide-ranging experience in the banking sector, having occupied a number of senior executive positions in international banks. He spent 7 years working for Crédit Lyonnais International before joining KPMG France as a Management Consultant in 1995. In 1997, he was appointed as Head of Information Technology and Organisation of Banque Robeco France (a Personal Banking Unit of the Rabobank Group). From 2000 to 2008, he was appointed Chief Information Officer and Senior Vice-President Business Development of ING Direct, to establish the units both in France and the UK. From 2008 to 2011, he launched and was the Chief Operating Officer of BforBank, the direct banking unit of Crédit Agricole. He then acted as Chief Operating Officer, Chief Business Development Officer and Executive Board Director of MeDirect Bank, a privately owned investment and wealth bank operating in Malta and Belgium prior to joining MCB Ltd.",
    "tagLine": "MAURITIUS COMMERCIAL BANK LIMITED",
    "profilePicture": "https://sessionize.com/image/5136-400o400o2-Sa2gZpusKijeRYoR5EB6iL.jpg",
    "sessions": [
      {
        "id": 303855,
        "name": "Embracing a new era of automation, tools, and platforms at MCB"
      }
    ],
    "isTopSpeaker": false,
    "links": [],
    "questionAnswers": [],
    "categories": []
  },
  {
    "id": "dc62c3be-2c87-4d15-b326-24f087431a46",
    "firstName": "Vishnoo",
    "lastName": "Luximan",
    "fullName": "Vishnoo Luximan",
    "bio": "Born in 1962, Vishnoo Luximan worked as Assistant Personnel & Public Relations Officer at the Constance & La Gaieté SE Company Ltd from 1983 to 1988.\r\nHe joined Deep River-Beau Champ Ltd (DRBC) as Assistant Personnel Manager/Public Relations Officer in 1988. He was promoted to the position of Personnel Manager/Public Relations Officer with the same company in 1990.\r\nHe was appointed Human Resources Manager of DRBC in 2002 and, as such, provided advice and services to 7 companies of the CIEL Group, including TPC Ltd, found in Tanzania.\r\nHe cumulated the responsibility of Acting Secretary of the Mauritius Sugar Producers’ Association with that of Human Resources Manager of DRBC from September to December 2005. \r\nHe joined the SWAN Group in 2006 as Senior Manager, Group Human Resources, and was promoted to the position of Chief Human Capital Officer in 2018.\r\nHe holds a Diploma in Public Relations, a Diploma in Human Resource Management, a Diploma in Business Management, and an MSc. in Human Resources Management. He is a Professional Member of the Singapore Human Resource Institute.\r\n",
    "tagLine": "Chief Human Capital Officer at SWAN",
    "profilePicture": "https://sessionize.com/image/cdd9-400o400o2-RkQe8QiAGvTWxVxpAG1Mzm.jpg",
    "sessions": [
      {
        "id": 380243,
        "name": "Enhancing the quality of working life "
      }
    ],
    "isTopSpeaker": false,
    "links": [],
    "questionAnswers": [],
    "categories": []
  },
  {
    "id": "c32c4eec-95fb-4bcf-9241-299b236819fd",
    "firstName": "Vishwadev",
    "lastName": "Bhundhoo",
    "fullName": "Vishwadev Bhundhoo",
    "bio": "Senior Project Manager Tech. Multi-techno developer, architect and technology professional.",
    "tagLine": "Publicis Prodigious, Senior Project Manager Tech",
    "profilePicture": "https://sessionize.com/image/44af-400o400o2-WXSbXA275NTD1CzrrmasUN.jpg",
    "sessions": [
      {
        "id": 384970,
        "name": "Boosting your web traffic in 2022"
      }
    ],
    "isTopSpeaker": false,
    "links": [
      {
        "title": "LinkedIn",
        "url": "https://www.linkedin.com/in/vishwadev-bhundhoo-906b884",
        "linkType": "LinkedIn"
      }
    ],
    "questionAnswers": [],
    "categories": []
  },
  {
    "id": "e0595a07-37aa-4518-9312-3f2654e96b0a",
    "firstName": "Vithilinga ",
    "lastName": "Dirooven",
    "fullName": "Vithilinga Dirooven",
    "bio": "Kavi is an Information Technology professional with more than 20 years of working experience in the field of ICT promotion, development and advisory matters. \r\n\r\nHe holds a Degree in Computer Science. He currently works in the capacity of Business Analyst of the Planning Research and Development section at the National Computer Board.\r\n\r\nHe has been associated with several ICT projects and initiatives ranging from technical implementation of ICT projects to the elaboration of ICT related policies. He is currently focused on Open Data projects driven by the National Open Data Initiatives of the Government. ",
    "tagLine": "Business Analyst National Computer Board",
    "profilePicture": "https://sessionize.com/image/52ae-400o400o2-ra7rmjXNJCGZDCJG6fdZy2.jpg",
    "sessions": [
      {
        "id": 389176,
        "name": "National Geo and IOT Portals  and Mobile Applications"
      }
    ],
    "isTopSpeaker": false,
    "links": [],
    "questionAnswers": [],
    "categories": []
  },
  {
    "id": "768c1d9c-0ea3-4cb7-9bca-f0aad08dfa9a",
    "firstName": "Yashin",
    "lastName": "Soraballee",
    "fullName": "Yashin Soraballee",
    "bio": "Currently a technical project manager with responsibilities in team and project management. Being a coding enthusiast, I frequently build & release applications.",
    "tagLine": "Senior Project Manager",
    "profilePicture": "https://sessionize.com/image/d055-400o400o2-wpqgWAovqx8nAPtJBgALUP.jpg",
    "sessions": [
      {
        "id": 384970,
        "name": "Boosting your web traffic in 2022"
      }
    ],
    "isTopSpeaker": false,
    "links": [
      {
        "title": "Twitter",
        "url": "https://twitter.com/Yashin_So",
        "linkType": "Twitter"
      },
      {
        "title": "LinkedIn",
        "url": "https://www.linkedin.com/in/yashinsoraballee/",
        "linkType": "LinkedIn"
      },
      {
        "title": "Blog",
        "url": "http://www.yashinblog.xyz/",
        "linkType": "Blog"
      }
    ],
    "questionAnswers": [],
    "categories": []
  },
  {
    "id": "59e993c0-6414-422d-a843-805464c6ff4a",
    "firstName": "Yovan",
    "lastName": "Fowdar",
    "fullName": "Yovan Fowdar",
    "bio": "Driven solely by passion  he is ready to take the challenge to experiment and learn new things, He has shouldered various responsibilities at management position in technical and technological companies . He loves getting  his hands dirty  even if it is not his responsibility  just to get the job done .  Great problem solver in both technical  and managerial fields, \r\n\r\nUser of Linux since  1993 ( Linux Slackware)  has started exploring and experimenting with Open Source OS.  Loves electronics  and been playing with since the age of 10.   \r\n\r\nWork experience : - \r\n\r\nUnisys   -  Server & Network implementation under unix  for the supreme court of Mauritius  (1 Year)\r\n\r\nMauritius Telecom -- Joined the then newly created Data Unit  (Birth of Internet in Mauritius)  worked in various fields, public telephone switch, commissioning of international ISDN links, trainer for local staffs and for African international telecom operators.  (7.5 Years)\r\n\r\nBNP Parisbas Mauritius Branch - Assistant IT manager  , implementation of  intranet, VPN , remote dial up access, administration under AIX, SCO , Windows Server(1 Year) \r\n\r\nCard Business System and Applitel Ltd --  Technical Director ( Gemalto Smart Cards , VPN , setup of a data center , Kenya , Madagascar)  \r\nExpand Technology Holding  -  Technical Director  + R&D Director  + Software development Manager + Board Director of Mauritius and Kenya .  Ten years of experience in Smart Cards security, VPN infrastructure, IP Telephony, servers physical and virtualized.   (12 Years)\r\n\r\n\r\nGeneration Plus Ltd -- Founder (main activities IoT, Consultancy, Build solutions & devices  around micro controllers and SBC) \r\n\r\nMauritius Maker Community -- Co-founder  where he plays an active role in promoting  innovative technology oriented initiatives (AI, Robotics, IoT, 3D Printing, microcontrollers ,\r\n\r\n1st  Makerspace in Mauritius,  - Founded the 1st  Mauritian  Maker Space  . \r\n",
    "tagLine": "Mauritius Maker Community / Founder & Managing Director Generation Plus Ltd",
    "profilePicture": "https://sessionize.com/image/be61-400o400o2-wencUXagodhSxT4WMVzQsa.jpg",
    "sessions": [
      {
        "id": 302688,
        "name": "ESP8266 a practical approach"
      }
    ],
    "isTopSpeaker": false,
    "links": [
      {
        "title": "Twitter",
        "url": "https://twitter.com/yovanfowdar",
        "linkType": "Twitter"
      },
      {
        "title": "LinkedIn",
        "url": "https://www.linkedin.com/in/yovan/",
        "linkType": "LinkedIn"
      },
      {
        "title": "Blog",
        "url": "https://www.facebook.com/groups/mauritiusmakers",
        "linkType": "Blog"
      }
    ],
    "questionAnswers": [],
    "categories": []
  },
  {
    "id": "068bb65a-6992-40fe-9ff2-77c989e5029c",
    "firstName": "Yuvraj",
    "lastName": "Keenoo",
    "fullName": "Yuvraj Keenoo",
    "bio": "Currently working as Tech Lead at MCB.\r\nHave experience in Oracle ERP, Angular, Spring Boot and Camunda.",
    "tagLine": "Tech Lead at MCB",
    "profilePicture": "https://sessionize.com/image/2cb5-400o400o2-UDiRepvtaSp1mTQYcnWjLe.jpg",
    "sessions": [
      {
        "id": 373082,
        "name": "Camunda - The Universal Process Orchestrator"
      }
    ],
    "isTopSpeaker": false,
    "links": [
      {
        "title": "Twitter",
        "url": "https://twitter.com/lovvyrules",
        "linkType": "Twitter"
      },
      {
        "title": "LinkedIn",
        "url": "https://mu.linkedin.com/in/yuvrajkeenoo/en",
        "linkType": "LinkedIn"
      },
      {
        "title": "Blog",
        "url": "https://lovvy.wordpress.com/",
        "linkType": "Blog"
      }
    ],
    "questionAnswers": [],
    "categories": []
  },
  {
    "id": "d79565ab-04a6-4a58-a25e-71c0e2e94924",
    "firstName": "Zulaika",
    "lastName": "Sunthbocus",
    "fullName": "Zulaika Sunthbocus",
    "bio": "Zulaika Sunthbocus is Co-founder and ex Director of Spoon Consulting, one of the most innovative IT consulting and software development companies of Mauritius regrouping more than 130 experts to accompany our clients throughout the world including Mauritius in their digital transformation journey. \r\n\r\nZulaika is highly engaged in the IT sector : She works in close collaboration with the IT institutions, sharing her ideas to leverage the digital incentives in the private and public sectors and connecting both foreign and local  leaders of the IT ecosystem. \r\n\r\nOne of the major strengths of her leadership style is her ability to create talents and to make her people step out of their comfort zone to become high achievers. \r\n\r\nZulaika was the only woman nominee of the IBL Tecoma Award and won the ‘Coup de Coeur du Jury’ award in 2017. This award largely contributed in recognizing Zulaika as a role model for Women Entrepreneurs. \r\nBesides she is an active member of AMFCE ( Agence Mauricienne des Femmes Chef d’entreprise) sustaining the new women entrepreneurship culture of Mauritius.\r\n\r\nZulaika is a passionate woman who also practices quite a number of sports like scuba diving, golf, trails amongst others, Last but not least, she makes an optimal use of technology to travel the world and work from wherever to keep her business going.    \r\n",
    "tagLine": "Co founder & ex Director of Spoon Consulting Ltd.",
    "profilePicture": "https://sessionize.com/image/be8d-400o400o2-c23467c0-6713-46d4-8184-6969c467270c.jpg",
    "sessions": [
      {
        "id": 301384,
        "name": "Artificial Intelligence : Benefits & Risks"
      }
    ],
    "isTopSpeaker": false,
    "links": [
      {
        "title": "LinkedIn",
        "url": "https://www.linkedin.com/in/zulaika-sunthbocus-3419b713/",
        "linkType": "LinkedIn"
      }
    ],
    "questionAnswers": [],
    "categories": []
  }
]